fuzzless/__init__.py
fuzzless/app.py
fuzzless/file_reader.py
fuzzless/pager_modal.py
fuzzless/pager_widget.py
fuzzless/patterns_modal.py
fuzzless/patterns_widget.py
fuzzless/presets_widget.py
fuzzless/vertical_tabs.py
fuzzless-0.1.0.dist-info/METADATA
fuzzless-0.1.0.dist-info/WHEEL
fuzzless-0.1.0.dist-info/entry_points.txt
fuzzless-0.1.0.dist-info/licenses/LICENSE
fuzzless-0.1.0.dist-info/RECORD
