Metadata-Version: 2.4
Name: fuzzless
Version: 0.1.0
Summary: A simple Hello World Textual TUI application
License-File: LICENSE
Requires-Python: >=3.13
Requires-Dist: regex>=2025.11.3
Requires-Dist: textual>=6.8.0
